becoder/__init__.py
becoder/dynamo.py
becoder_pkg/__init__.py
becoder_pkg/dynamo.py
db_pkg/__init__.py
db_pkg/dynamo.py
becoder_pkg-0.1.2.dist-info/METADATA
becoder_pkg-0.1.2.dist-info/WHEEL
becoder_pkg-0.1.2.dist-info/top_level.txt
becoder_pkg-0.1.2.dist-info/RECORD
