Metadata-Version: 2.1
Name: becoder-pkg
Version: 0.1.2
Summary: Be-Coder package(empty value is set "NULL"
Home-page: https://github.com/nj0034
Author: Lee Nam Jin
Author-email: nj@devhi.me
License: UNKNOWN
Download-URL: https://github.com/nj0034
Keywords: liquibase,db migration
Platform: UNKNOWN
Classifier: Programming Language :: Python :: 3
Classifier: Programming Language :: Python :: 3.2
Classifier: Programming Language :: Python :: 3.3
Classifier: Programming Language :: Python :: 3.4
Classifier: Programming Language :: Python :: 3.5
Classifier: Programming Language :: Python :: 3.6
Classifier: Programming Language :: Python :: 3.7
Requires-Python: >=3
